allzparkdemo/__init__.py
allzparkdemo/__main__.py
allzparkdemo/__version__.py
allzparkdemo/allzparkconfig.py
allzparkdemo/build.py
allzparkdemo/rezconfig.py
allzparkdemo/version.py
allzparkdemo/dev/README.md
allzparkdemo/dev/aftereffects/package.py
allzparkdemo/dev/aftereffects/build/resources/icon_256x256.png
allzparkdemo/dev/aftereffects/resources/icon_256x256.png
allzparkdemo/dev/alita/package.py
allzparkdemo/dev/alita/build/resources/icon_32x32.png
allzparkdemo/dev/alita/build/resources/icon_64x64.png
allzparkdemo/dev/alita/resources/icon_32x32.png
allzparkdemo/dev/alita/resources/icon_64x64.png
allzparkdemo/dev/base/package.py
allzparkdemo/dev/blender/package.py
allzparkdemo/dev/blender/build/resources/icon_64.png
allzparkdemo/dev/blender/build/resources/readme.txt
allzparkdemo/dev/blender/resources/icon_64.png
allzparkdemo/dev/blender/resources/readme.txt
allzparkdemo/dev/broken_package/README.md
allzparkdemo/dev/broken_package/1.0.bad_env/package.py
allzparkdemo/dev/broken_package/1.1.bad_commands/package.py
allzparkdemo/dev/broken_package/1.2.bad_alias/package.py
allzparkdemo/dev/core-pipeline/package.py
allzparkdemo/dev/core-pipeline/python/core_pipeline/__init__.py
allzparkdemo/dev/default_project/README.md
allzparkdemo/dev/default_project/package.py
allzparkdemo/dev/default_project/template.py
allzparkdemo/dev/default_project/bin/create.bat
allzparkdemo/dev/default_project/bin/create.py
allzparkdemo/dev/default_project/build/README.md
allzparkdemo/dev/default_project/build/template.py
allzparkdemo/dev/default_project/build/bin/create.bat
allzparkdemo/dev/default_project/build/bin/create.py
allzparkdemo/dev/dev-maya/package.py
allzparkdemo/dev/dev-maya/bin/maya.bat
allzparkdemo/dev/dev-maya/bin/mayabatch.bat
allzparkdemo/dev/dev-maya/bin/mayagui_lic.bat
allzparkdemo/dev/dev-maya/bin/mayapy.bat
allzparkdemo/dev/dev-maya/bin/render.bat
allzparkdemo/dev/dev-maya/build/bin/maya.bat
allzparkdemo/dev/dev-maya/build/bin/mayabatch.bat
allzparkdemo-1.0.23.dist-info/LICENSE
allzparkdemo-1.0.23.dist-info/METADATA
allzparkdemo-1.0.23.dist-info/WHEEL
allzparkdemo-1.0.23.dist-info/entry_points.txt
allzparkdemo-1.0.23.dist-info/top_level.txt
allzparkdemo-1.0.23.dist-info/RECORD
